KRidge_GIN/KRidge.py
KRidge_GIN/__init__.py
KRidge_GIN-1.0.0.dist-info/LICENSE
KRidge_GIN-1.0.0.dist-info/METADATA
KRidge_GIN-1.0.0.dist-info/WHEEL
KRidge_GIN-1.0.0.dist-info/top_level.txt
KRidge_GIN-1.0.0.dist-info/RECORD
